mathpad/__init__.py
mathpad/_global_options.py
mathpad/codegen.py
mathpad/core/__init__.py
mathpad/core/_generate_units_py.py
mathpad/core/common_vals.py
mathpad/core/dimensions.py
mathpad/core/equation.py
mathpad/core/frame.py
mathpad/core/matrix.py
mathpad/core/units.py
mathpad/core/val.py
mathpad/core/vector.py
mathpad/core/vector_space.py
mathpad/library/constants.py
mathpad/library/electrical.py
mathpad/library/mathpad_constructor.py
mathpad/library/mechanic.py
mathpad/library/trigonometry.py
mathpad/maths/__init__.py
mathpad/maths/algebra.py
mathpad/maths/calculus.py
mathpad/maths/functions.py
mathpad/maths/solve.py
mathpad/maths/trigonometry.py
mathpad/simulate_dynamic_system.py
mathpad/sympy_extensions/SymbolicMatrixFunction.py
mathpad/sympy_extensions/__init__.py
mathpad/sympy_extensions/monkeypatch.py
mathpad/sympy_extensions/monkeypatch_ArrayDerivative___len__and__iter__.py
mathpad/sympy_extensions/monkeypatch_MatrixOperations_subs.py
mathpad/sympy_extensions/monkeypatch_VectorLatexPrinter_print_Derivative.py
mathpad/viz/viz2d.py
mathpad/viz/viz3d.py
mathpad-2.1.0.dist-info/LICENSE
mathpad-2.1.0.dist-info/METADATA
mathpad-2.1.0.dist-info/WHEEL
mathpad-2.1.0.dist-info/RECORD
