Metadata-Version: 2.1
Name: mathpad
Version: 2.1.0
Summary: Simplified interface to Sympy for solving physics, engineering and maths problems
Home-page: https://github.com/CallumJHays/mathpad
License: MIT
Author: Callum J Hays
Author-email: callumjhays@gmail.com
Requires-Python: >=3.7,<3.11
Classifier: Development Status :: 2 - Pre-Alpha
Classifier: Intended Audience :: Developers
Classifier: License :: OSI Approved :: MIT License
Classifier: Natural Language :: English
Classifier: Operating System :: OS Independent
Classifier: Programming Language :: Python :: 3
Classifier: Programming Language :: Python :: 3.7
Classifier: Programming Language :: Python :: 3.8
Classifier: Programming Language :: Python :: 3.9
Classifier: Programming Language :: Python :: 3.10
Classifier: Topic :: Software Development :: Libraries
Provides-Extra: viz
Requires-Dist: numpy (>=1.20,<2.0)
Requires-Dist: scipy (>=1.7.1,<2.0.0)
Requires-Dist: sympy (>=1.8,<2.0)
Requires-Dist: typing-extensions (>=4.0.0,<5.0.0)
Project-URL: Bug Tracker, https://github.com/CallumJHays/mathpad/issues
Project-URL: Changelog, https://mathpad.readthedocs.io/changelog.html
Project-URL: Documentation, https://mathpad.readthedocs.io
Project-URL: Repository, https://github.com/CallumJHays/mathpad
